README.md
setup.cfg
setup.py
easyTX/__init__.py
easyTX/client.py
easyTX/constants.py
easyTX/server.py
easyTX.egg-info/PKG-INFO
easyTX.egg-info/SOURCES.txt
easyTX.egg-info/dependency_links.txt
easyTX.egg-info/requires.txt
easyTX.egg-info/top_level.txt