Metadata-Version: 2.1
Name: easyTX
Version: 2.0
Summary: Module to exchange data in any form (video or string) from one PC to another over the same network.
Home-page: https://github.com/VDHARV/easyTX-2.0
Author: VDHARV
Author-email: vdharv4bharat@gmail.com
License: MIT
Platform: UNKNOWN
Classifier: License :: OSI Approved :: MIT License
Classifier: Programming Language :: Python :: 3
Classifier: Programming Language :: Python :: 3.9
